{"stats":{"minecraft:custom":{"minecraft:interact_with_crafting_table":198,"minecraft:open_barrel":13,"minecraft:eat_cake_slice":11,"minecraft:leave_game":35,"minecraft:time_since_death":243125,"minecraft:damage_blocked_by_shield":24737,"minecraft:deaths":91,"minecraft:jump":7912,"minecraft:enchant_item":2,"minecraft:interact_with_furnace":103,"minecraft:play_record":2,"minecraft:interact_with_cartography_table":1,"minecraft:sleep_in_bed":29,"minecraft:damage_dealt":290547,"minecraft:interact_with_smoker":9,"minecraft:horse_one_cm":877840,"minecraft:interact_with_anvil":39,"minecraft:sneak_time":40705,"minecraft:interact_with_lectern":3,"minecraft:tune_noteblock":4,"minecraft:time_since_rest":4885,"minecraft:swim_one_cm":129224,"minecraft:fly_one_cm":2788381,"minecraft:open_chest":1248,"minecraft:fall_one_cm":119028,"minecraft:animals_bred":4,"minecraft:sprint_one_cm":3503198,"minecraft:drop":490,"minecraft:play_noteblock":1,"minecraft:talked_to_villager":3,"minecraft:walk_on_water_one_cm":455430,"minecraft:play_one_minute":1416686,"minecraft:player_kills":1,"minecraft:crouch_one_cm":72350,"minecraft:mob_kills":1032,"minecraft:climb_one_cm":18668,"minecraft:walk_one_cm":5581069,"minecraft:walk_under_water_one_cm":292621,"minecraft:boat_one_cm":89684,"minecraft:damage_taken":105049,"minecraft:damage_absorbed":743,"minecraft:trigger_trapped_chest":2},"minecraft:dropped":{"minecraft:iron_sword":3,"minecraft:lapis_lazuli":1,"minecraft:oak_pressure_plate":1,"minecraft:glass_bottle":6,"lycanitesmobs:poisongland":5,"minecraft:mossy_stone_brick_stairs":3,"minecraft:cracked_stone_bricks":10,"minecraft:dirt":94,"minecraft:grass":5,"quark:cobbled_deepslate":1,"minecraft:jungle_sapling":1,"minecraft:wooden_sword":1,"minecraft:gold_nugget":11,"minecraft:bone_meal":2,"minecraft:phantom_membrane":4,"minecraft:sand":2,"minecraft:sugar":4,"minecraft:iron_pickaxe":2,"minecraft:fermented_spider_eye":4,"minecraft:white_wool":5,"minecraft:bone":52,"minecraft:sugar_cane":1,"lycanitesmobs:lushstonepillar":7,"minecraft:iron_nugget":11,"minecraft:golden_chestplate":1,"minecraft:birch_sapling":2,"minecraft:obsidian":2,"minecraft:rotten_flesh":122,"minecraft:oak_planks":40,"minecraft:tipped_arrow":4,"minecraft:leather_boots":1,"lycanitesmobs:cooked_arisaur_meat":1,"minecraft:leather_leggings":2,"minecraft:stone_brick_stairs":4,"minecraft:egg":1,"minecraft:golden_boots":3,"minecraft:wheat_seeds":7,"minecraft:tnt":2,"lycanitesmobs:lushstonebrick":25,"lycanitesmobs:equipmentpart_bansheeeye":4,"minecraft:feather":7,"lycanitesmobs:saddle_beast":1,"minecraft:oak_fence":1,"minecraft:iron_helmet":2,"minecraft:cobblestone":27,"minecraft:prismarine_crystals":2,"minecraft:spruce_door":1,"minecraft:chainmail_helmet":1,"minecraft:coal":88,"minecraft:polished_andesite":6,"minecraft:cobweb":4,"minecraft:ink_sac":2,"minecraft:rose_bush":4,"minecraft:potion":1,"minecraft:oak_stairs":1,"minecraft:mossy_cobblestone_stairs":7,"minecraft:smooth_stone":2,"minecraft:iron_shovel":1,"minecraft:string":20,"minecraft:blue_carpet":14,"minecraft:furnace":1,"minecraft:bricks":1,"minecraft:stone_sword":4,"minecraft:cocoa_beans":18,"minecraft:white_carpet":9,"lycanitesmobs:equipmentpart_grueclaw":2,"minecraft:clay_ball":15,"minecraft:iron_boots":4,"lycanitesmobs:lushstonepolished":3,"minecraft:pumpkin_seeds":3,"minecraft:diamond_sword":5,"minecraft:stone":9,"minecraft:flower_pot":5,"minecraft:stone_pressure_plate":5,"minecraft:spider_eye":36,"minecraft:stone_bricks":12,"minecraft:magma_block":12,"minecraft:black_wool":1,"lycanitesmobs:scorchfireballcharge":3,"minecraft:soul_sand":23,"minecraft:ender_pearl":1,"minecraft:golden_pickaxe":2,"lycanitesmobs:aetherwavecharge":3,"minecraft:leather":5,"minecraft:flint":2,"minecraft:cod":2,"minecraft:music_disc_13":1,"minecraft:orange_carpet":1,"minecraft:snowball":1,"minecraft:gravel":3,"quark:root_item":4,"minecraft:beetroot":1,"lycanitesmobs:raw_arisaur_meat":5,"minecraft:chainmail_chestplate":2,"minecraft:chiseled_stone_bricks":2,"minecraft:poppy":4,"minecraft:leather_chestplate":3,"minecraft:gunpowder":5,"minecraft:chainmail_boots":1,"minecraft:iron_bars":19,"minecraft:arrow":4,"minecraft:quartz":52,"minecraft:netherrack":1,"lycanitesmobs:geistliver":4,"minecraft:golden_helmet":2,"minecraft:lilac":3,"minecraft:mossy_cobblestone":10,"scalinghealth:cursed_heart":3,"minecraft:minecart":1,"minecraft:prismarine_shard":3,"lycanitesmobs:lushstonechiseled":2,"minecraft:melon_slice":2,"lycanitesmobs:equipmentpart_darklingskull":1,"minecraft:iron_leggings":1,"minecraft:polished_andesite_stairs":7,"minecraft:iron_axe":3,"minecraft:dandelion":1,"minecraft:nether_wart":23,"minecraft:blaze_rod":2,"minecraft:ender_eye":2,"minecraft:filled_map":1,"minecraft:shield":2,"minecraft:iron_chestplate":3,"minecraft:andesite":4,"minecraft:mossy_stone_bricks":25,"minecraft:oak_sapling":9,"minecraft:slime_ball":20,"minecraft:wooden_pickaxe":1,"minecraft:music_disc_mellohi":1,"minecraft:magma_cream":4,"scalinghealth:enchanted_heart":60},"minecraft:mined":{"minecraft:blue_carpet":3,"minecraft:white_bed":4,"minecraft:acacia_log":2,"minecraft:oak_pressure_plate":1,"minecraft:coal_block":1,"minecraft:chiseled_stone_bricks":4,"minecraft:spawner":165,"minecraft:tall_seagrass":4,"minecraft:mossy_cobblestone_stairs":5,"minecraft:fire":5,"minecraft:nether_brick_stairs":1,"minecraft:enchanting_table":1,"minecraft:oak_stairs":3,"minecraft:sandstone_slab":1,"minecraft:brown_mushroom":1,"minecraft:red_bed":2,"minecraft:kelp_plant":18,"minecraft:smoker":1,"minecraft:torch":25,"minecraft:melon":1,"minecraft:polished_andesite_stairs":6,"minecraft:bricks":3,"lycanitesmobs:smitefire":7,"minecraft:wheat":2,"minecraft:lilac":1,"minecraft:stone_brick_stairs":4,"minecraft:grass":91,"lycanitesmobs:lushstonebrick":102,"minecraft:light_gray_stained_glass_pane":7,"minecraft:mossy_cobblestone":62,"lycanitesmobs:lushstonechiseled":82,"minecraft:nether_bricks":65,"minecraft:redstone_wire":1,"minecraft:kelp":6,"minecraft:andesite":482,"quark:smooth_basalt":6,"minecraft:mossy_stone_brick_stairs":9,"minecraft:cobblestone_slab":7,"minecraft:vine":36,"minecraft:bone_block":3,"minecraft:white_wool":20,"minecraft:oak_slab":3,"minecraft:soul_sand":7,"quark:oak_chest":6,"minecraft:lily_of_the_valley":2,"minecraft:smooth_sandstone":1,"minecraft:tall_grass":5,"minecraft:orange_carpet":2,"minecraft:black_stained_glass":2,"minecraft:white_carpet":5,"minecraft:birch_leaves":34,"quark:deepslate":20,"minecraft:mycelium":12,"minecraft:gravel":12,"minecraft:cobweb":39,"minecraft:stone_bricks":39,"lycanitesmobs:scorchfire":25,"lycanitesmobs:lushstonetile":5,"quark:root":69,"minecraft:stone_pressure_plate":2,"minecraft:spruce_planks":1,"minecraft:andesite_stairs":1,"minecraft:cobblestone_stairs":1,"minecraft:potted_cactus":2,"minecraft:grass_block":1744,"minecraft:smooth_stone":3,"minecraft:mossy_cobblestone_slab":4,"minecraft:iron_ore":17,"lycanitesmobs:lushstonepillar":35,"minecraft:anvil":2,"minecraft:iron_bars":34,"lycanitesmobs:lushstonepolished":22,"minecraft:quartz_block":7,"minecraft:clay":5,"minecraft:potted_jungle_sapling":1,"minecraft:poppy":5,"quark:stone_speleothem":1,"minecraft:chest":6,"minecraft:cobblestone":235,"lycanitesmobs:quickweb":3,"minecraft:oak_planks":38,"minecraft:iron_door":2,"minecraft:wall_torch":27,"minecraft:seagrass":8,"minecraft:birch_log":123,"quark:marble":16,"minecraft:tnt":3,"minecraft:oak_log":330,"minecraft:sand":345,"minecraft:dirt":1311,"minecraft:netherrack":7,"minecraft:oak_leaves":178,"minecraft:furnace":6,"lycanitesmobs:lushcrystal":2,"minecraft:gold_block":26,"minecraft:bookshelf":4,"minecraft:stone":2026,"quark:cobbedstone":8,"lycanitesmobs:doomfire":2,"lycanitesmobs:shadowfire":9,"minecraft:polished_granite":1,"minecraft:oak_fence":27,"minecraft:crafting_table":18,"minecraft:rose_bush":7,"minecraft:stone_slab":1,"minecraft:lily_pad":1,"minecraft:lime_bed":6,"minecraft:grass_path":1,"minecraft:black_wool":1,"minecraft:coal_ore":195,"minecraft:cracked_stone_bricks":70,"minecraft:polished_andesite":64,"minecraft:mossy_stone_bricks":51,"minecraft:birch_fence":5},"minecraft:picked_up":{"minecraft:wooden_axe":10,"lycanitesmobs:quillcharge":9,"minecraft:iron_chestplate":22,"minecraft:chainmail_boots":8,"minecraft:flower_pot":6,"minecraft:anvil":3,"minecraft:prismarine_shard":3,"apotheosis:rare_tome":1,"minecraft:lead":10,"minecraft:stone_slab":1,"minecraft:diamond_sword":18,"minecraft:oak_stairs":11,"minecraft:enchanted_book":21,"lycanitesmobs:raw_arisaur_meat":81,"lycanitesmobs:equipmentpart_geonachspear":2,"minecraft:string":864,"lycanitesmobs:raw_aspid_meat":61,"lycanitesmobs:equipmentpart_geonachfist":22,"minecraft:beetroot":2,"minecraft:diamond_leggings":14,"minecraft:gold_nugget":53,"lycanitesmobs:immunizer":2,"minecraft:spruce_planks":1,"quark:root_item":160,"minecraft:melon_slice":8,"minecraft:golden_helmet":10,"lycanitesmobs:soulstone_plant":4,"minecraft:acacia_log":2,"lycanitesmobs:geistliver":58,"minecraft:golden_chestplate":19,"minecraft:brown_carpet":2,"lycanitesmobs:summoningstaff":3,"minecraft:stone_sword":38,"artifacts:lucky_scarf":1,"lycanitesmobs:saddle_elemental":2,"lycanitesmobs:soulstone_undead":1,"lycanitesmobs:lushcrystal":2,"lycanitesmobs:equipmentpart_bansheeeye":26,"minecraft:blaze_rod":117,"minecraft:iron_bars":62,"quark:marble":16,"minecraft:snowball":8,"minecraft:birch_log":140,"minecraft:magma_block":12,"minecraft:mossy_cobblestone_slab":2,"minecraft:feather":66,"minecraft:cooked_beef":133,"minecraft:iron_door":1,"minecraft:water_bucket":12,"artifacts:thorn_pendant":11,"lycanitesmobs:poopcharge":34,"minecraft:smoker":1,"minecraft:flint":27,"minecraft:map":10,"lycanitesmobs:aetherwavecharge":28,"apotheosis:digger_book":1,"minecraft:rabbit":7,"minecraft:diamond_helmet":11,"minecraft:glowstone_dust":48,"lycanitesmobs:raw_yale_meat":25,"patchouli:guide_book":4,"apotheosis:null_book":1,"scalinghealth:enchanted_heart":120,"minecraft:ink_sac":3,"minecraft:fermented_spider_eye":18,"lycanitesmobs:arcanelaserstormcharge":50,"quark:cobbled_deepslate":9,"minecraft:polished_andesite":137,"lycanitesmobs:scorchfireballcharge":172,"quark:cobbedstone":5,"minecraft:chainmail_helmet":4,"minecraft:horse_spawn_egg":1,"minecraft:golden_horse_armor":1,"minecraft:bread":70,"minecraft:bricks":9,"minecraft:diamond_pickaxe":3,"minecraft:crafting_table":36,"minecraft:nether_wart":41,"minecraft:clay_ball":120,"minecraft:leather_leggings":12,"minecraft:golden_pickaxe":3,"apotheosis:weapon_book":1,"minecraft:red_bed":2,"lycanitesmobs:embercharge":19,"minecraft:flint_and_steel":4,"minecraft:compass":4,"minecraft:white_carpet":26,"minecraft:iron_shovel":5,"minecraft:cracked_stone_bricks":83,"minecraft:beef":8,"minecraft:poppy":6,"minecraft:jungle_sapling":1,"minecraft:iron_nugget":48,"minecraft:minecart":3,"minecraft:chest":8,"minecraft:birch_sapling":32,"lycanitesmobs:raw_maka_meat":15,"lycanitesmobs:soulstone_aberration":6,"minecraft:egg":7,"minecraft:stone":517,"minecraft:oak_door":18,"minecraft:music_disc_mellohi":1,"minecraft:spruce_fence":4,"minecraft:carrot":6,"minecraft:prismarine_crystals":2,"minecraft:blue_carpet":32,"minecraft:tnt":5,"minecraft:diamond_chestplate":4,"lycanitesmobs:aquapulsecharge":12,"minecraft:cooked_cod":5,"lycanitesmobs:raw_jouste_meat":13,"minecraft:shears":2,"minecraft:diamond_boots":4,"lycanitesmobs:chaosorbcharge":60,"minecraft:gold_ingot":282,"minecraft:mutton":12,"minecraft:white_wool":29,"minecraft:bone_block":184,"minecraft:lime_bed":9,"lycanitesmobs:equipmentpart_darklingskull":2,"minecraft:red_mushroom":3,"minecraft:filled_map":11,"minecraft:oak_log":723,"minecraft:lily_pad":4,"scalinghealth:bandages":37,"lycanitesmobs:veswax":42,"minecraft:golden_boots":14,"mowziesmobs:wrought_axe":3,"minecraft:paper":5,"minecraft:white_banner":1,"minecraft:spawner":2,"minecraft:apple":122,"minecraft:stone_bricks":44,"minecraft:kelp":9,"minecraft:stone_pickaxe":24,"minecraft:iron_ore":187,"minecraft:cobweb":5,"scalinghealth:power_crystal_shard":7,"minecraft:glass_bottle":14,"minecraft:iron_sword":31,"minecraft:polished_andesite_stairs":9,"lycanitesmobs:equipmentpart_grueclaw":3,"minecraft:gravel":10,"minecraft:leather_helmet":3,"minecraft:diamond_shovel":25,"minecraft:slime_ball":86,"minecraft:stone_axe":36,"lycanitesmobs:spawn_insect":3,"minecraft:diamond_axe":4,"minecraft:baked_potato":28,"minecraft:melon_seeds":11,"minecraft:ender_pearl":233,"lycanitesmobs:raw_chupacabra_meat":158,"minecraft:wheat":21,"artifacts:umbrella":10,"minecraft:potion":7,"lycanitesmobs:magmacharge":4,"minecraft:stone_brick_stairs":5,"lycanitesmobs:propolis":36,"lycanitesmobs:cooked_aspid_meat":8,"minecraft:iron_leggings":41,"minecraft:experience_bottle":540,"minecraft:smooth_stone":4,"minecraft:bucket":6,"lycanitesmobs:raw_bobeko_meat":4,"minecraft:rose_bush":4,"minecraft:cobblestone_slab":12,"minecraft:ender_eye":20,"quark:black_shard":8,"minecraft:iron_pickaxe":57,"lycanitesmobs:lushstonebrick":172,"minecraft:iron_boots":37,"minecraft:furnace":13,"minecraft:tipped_arrow":24,"minecraft:stick":1761,"minecraft:oak_fence":28,"minecraft:torch":2194,"lycanitesmobs:soulstone_avian":3,"minecraft:porkchop":22,"minecraft:vine":2,"quark:ancient_tome":5,"minecraft:quartz_block":6,"minecraft:cactus":1,"minecraft:rotten_flesh":685,"minecraft:obsidian":35,"minecraft:cod":5,"minecraft:blaze_powder":4,"lycanitesmobs:lifedraincharge":18,"minecraft:cobblestone":4895,"minecraft:enchanting_table":7,"minecraft:leather_chestplate":22,"minecraft:lilac":4,"minecraft:magma_cream":70,"minecraft:andesite":557,"minecraft:orange_carpet":16,"minecraft:golden_leggings":1,"minecraft:potato":1,"lycanitesmobs:lushstonepolished":30,"minecraft:lapis_lazuli":316,"minecraft:dirt":3241,"minecraft:polished_granite":1,"minecraft:name_tag":2,"minecraft:leather_boots":17,"minecraft:bone":583,"minecraft:bow":61,"minecraft:wheat_seeds":69,"lycanitesmobs:poisongland":47,"minecraft:mossy_stone_bricks":68,"minecraft:oak_planks":680,"minecraft:mossy_stone_brick_stairs":15,"lycanitesmobs:spectralboltcharge":86,"minecraft:cooked_porkchop":4,"lycanitesmobs:saddle_beast":2,"minecraft:music_disc_13":3,"lycanitesmobs:equipmentpart_entarm":9,"minecraft:oak_pressure_plate":1,"lycanitesmobs:raw_silex_meat":2,"minecraft:sand":316,"minecraft:lily_of_the_valley":2,"minecraft:mossy_cobblestone":96,"minecraft:sugar":4,"artifacts:golden_hook":2,"minecraft:diamond":277,"lycanitesmobs:lushstonetile":9,"minecraft:golden_apple":2,"minecraft:grass":7,"minecraft:bone_meal":1,"minecraft:emerald":157,"scalinghealth:cursed_heart":7,"minecraft:oak_sapling":166,"minecraft:netherrack":3,"minecraft:chorus_fruit":26,"minecraft:cocoa_beans":24,"minecraft:charcoal":6,"minecraft:chicken":5,"lycanitesmobs:cooked_arisaur_meat":41,"mutantbeasts:hulk_hammer":2,"minecraft:brown_mushroom":4,"minecraft:wooden_pickaxe":25,"minecraft:cooked_rabbit":4,"minecraft:gold_block":26,"minecraft:diamond_horse_armor":4,"minecraft:brick":9,"minecraft:shield":83,"minecraft:iron_axe":20,"minecraft:wooden_sword":6,"minecraft:birch_fence":5,"apotheosis:scrap_tome":1,"minecraft:andesite_stairs":2,"minecraft:oak_boat":2,"minecraft:player_head":1,"minecraft:sugar_cane":1,"lycanitesmobs:treat_beast":1,"minecraft:phantom_membrane":8,"lycanitesmobs:equipmentpart_naxiriseye":5,"lycanitesmobs:frostyfur":4,"quark:birch_chest":1,"minecraft:stone_pressure_plate":5,"minecraft:arrow":1945,"quark:smooth_basalt":7,"minecraft:nether_bricks":48,"lycanitesmobs:doomfireballcharge":17,"artifacts:running_shoes":10,"minecraft:saddle":7,"minecraft:leather":270,"minecraft:birch_planks":39,"minecraft:chainmail_chestplate":20,"lycanitesmobs:soulstone_beast":3,"lycanitesmobs:cooked_chupacabra_meat":929,"minecraft:gunpowder":262,"lycanitesmobs:raw_krake_meat":17,"scalinghealth:heart_crystal":21,"minecraft:wooden_hoe":7,"quark:blank_rune":1,"minecraft:cooked_mutton":20,"minecraft:rabbit_hide":6,"quark:deepslate":1,"lycanitesmobs:faeboltcharge":6,"minecraft:iron_ingot":785,"quark:tallow":18,"minecraft:stripped_oak_wood":4,"minecraft:soul_sand":200,"minecraft:music_disc_chirp":3,"minecraft:book":50,"minecraft:oak_slab":6,"scalinghealth:heart_crystal_shard":123,"minecraft:chiseled_stone_bricks":16,"minecraft:dandelion":1,"minecraft:quartz":278,"lycanitesmobs:soulstone_aquatic":1,"mowziesmobs:wrought_helmet":3,"minecraft:white_bed":7,"minecraft:gold_ore":39,"quark:oak_chest":6,"minecraft:spruce_door":1,"minecraft:spider_eye":86,"lycanitesmobs:lushstonechiseled":221,"minecraft:pumpkin_seeds":17,"lycanitesmobs:lushstonepillar":35,"minecraft:chainmail_leggings":19,"minecraft:iron_helmet":29,"lycanitesmobs:equipmentpart_conbabutt":6,"minecraft:mossy_cobblestone_stairs":9,"minecraft:black_wool":7,"minecraft:coal":4149},"minecraft:broken":{"minecraft:golden_boots":2,"minecraft:diamond_helmet":2,"minecraft:iron_boots":4,"minecraft:iron_chestplate":2,"minecraft:iron_leggings":3,"minecraft:chainmail_boots":1,"minecraft:wooden_sword":2,"minecraft:iron_sword":10,"minecraft:chainmail_leggings":1,"minecraft:stone_sword":4,"minecraft:chainmail_helmet":1,"minecraft:wooden_pickaxe":6,"minecraft:shield":1,"minecraft:iron_axe":2,"minecraft:iron_pickaxe":9,"minecraft:iron_helmet":5,"minecraft:golden_helmet":2,"minecraft:iron_shovel":3,"minecraft:leather_leggings":1,"minecraft:stone_pickaxe":3,"minecraft:chainmail_chestplate":1,"minecraft:stone_axe":2,"minecraft:wooden_axe":3,"minecraft:golden_chestplate":1,"minecraft:diamond_chestplate":1,"minecraft:leather_chestplate":1,"minecraft:leather_boots":4},"minecraft:killed":{"minecraft:cave_spider":32,"lycanitesmobs:roc":6,"lycanitesmobs:eyewig":1,"lycanitesmobs:gnekk":10,"minecraft:skeleton":71,"lycanitesmobs:yale":2,"minecraft:guardian":1,"minecraft:chicken":5,"lycanitesmobs:maka":5,"lycanitesmobs:erepede":1,"lycanitesmobs:naxiris":4,"lycanitesmobs:geken":18,"minecraft:magma_cube":14,"minecraft:parrot":18,"lycanitesmobs:jouste":9,"lycanitesmobs:aspid":4,"lycanitesmobs:arisaur":5,"lycanitesmobs:belphegor":8,"minecraft:pillager":4,"minecraft:zombie":253,"lycanitesmobs:raiko":1,"lycanitesmobs:warg":1,"minecraft:cow":2,"lycanitesmobs:trite":11,"lycanitesmobs:ostimien":3,"lycanitesmobs:herma":1,"quark:toretoise":1,"lycanitesmobs:darkling":6,"lycanitesmobs:conba":3,"mowziesmobs:ferrous_wroughtnaut":1,"lycanitesmobs:ent":12,"lycanitesmobs:balayang":1,"lycanitesmobs:joustealpha":1,"minecraft:husk":16,"lycanitesmobs:grue":21,"minecraft:wandering_trader":1,"lycanitesmobs:barghest":1,"lycanitesmobs:lycosa":33,"lycanitesmobs:jabberwock":3,"minecraft:enderman":2,"lycanitesmobs:krake":10,"minecraft:witch":3,"minecraft:zombified_piglin":1,"lycanitesmobs:zoataur":1,"lycanitesmobs:eechetik":1,"minecraft:spider":44,"lycanitesmobs:spriggan":5,"lycanitesmobs:volcan":4,"lycanitesmobs:necrovore":1,"lycanitesmobs:bobeko":1,"minecraft:bee":2,"minecraft:silverfish":4,"artifacts:mimic":1,"lycanitesmobs:sylph":2,"minecraft:pig":4,"minecraft:zombie_villager":4,"lycanitesmobs:geist":4,"lycanitesmobs:wraamon":9,"lycanitesmobs:gorgomite":1,"minecraft:creeper":13,"minecraft:sheep":5,"lycanitesmobs:thresher":1,"minecraft:trader_llama":1,"lycanitesmobs:argus":1,"minecraft:stray":27,"lycanitesmobs:geonach":12,"lycanitesmobs:vespidqueen":2,"lycanitesmobs:tremor":7,"lycanitesmobs:ghoul":58,"lycanitesmobs:banshee":45,"lycanitesmobs:reaper":11,"lycanitesmobs:aglebemu":1,"lycanitesmobs:silex":2,"lycanitesmobs:cinder":4,"lycanitesmobs:nymph":1,"minecraft:drowned":7,"lycanitesmobs:abaia":1,"lycanitesmobs:ventoraptor":1,"minecraft:bat":1,"lycanitesmobs:salamander":17,"lycanitesmobs:chupacabra":44,"lycanitesmobs:jengu":2,"lycanitesmobs:grigori":16,"mutantbeasts:mutant_zombie":1,"minecraft:wither_skeleton":10,"lycanitesmobs:afrit":25},"minecraft:crafted":{"minecraft:cooked_mutton":2,"minecraft:cooked_porkchop":4,"lycanitesmobs:cooked_jouste_meat":2,"lycanitesmobs:saddle_avian":1,"quark:oak_chest":8,"minecraft:iron_pickaxe":3,"minecraft:iron_block":3,"minecraft:gold_ingot":8,"lycanitesmobs:summoningstaff":2,"minecraft:leather_leggings":1,"minecraft:stone_pickaxe":5,"minecraft:golden_helmet":1,"minecraft:enchanting_table":1,"lycanitesmobs:cooked_aspid_meat":7,"lycanitesmobs:cooked_krake_meat":9,"minecraft:wooden_axe":3,"minecraft:iron_leggings":1,"minecraft:white_bed":1,"minecraft:oak_planks":144,"minecraft:cobblestone_slab":6,"minecraft:mossy_cobblestone_slab":6,"minecraft:stone_hoe":1,"minecraft:oak_fence":33,"lycanitesmobs:cooked_silex_meat":1,"minecraft:golden_boots":1,"minecraft:crafting_table":12,"minecraft:iron_helmet":1,"minecraft:wooden_pickaxe":4,"minecraft:iron_chestplate":1,"minecraft:birch_fence":6,"minecraft:stick":152,"minecraft:leather_chestplate":1,"minecraft:iron_ingot":17,"minecraft:stone_sword":7,"minecraft:shears":1,"minecraft:wooden_sword":3,"minecraft:oak_door":3,"lycanitesmobs:cooked_maka_meat":15,"minecraft:furnace":2,"lycanitesmobs:cooked_arisaur_meat":23,"lycanitesmobs:cooked_chupacabra_meat":42,"minecraft:flint_and_steel":1,"minecraft:iron_axe":2,"minecraft:cooked_cod":3,"minecraft:diamond_sword":1,"minecraft:iron_sword":7,"scalinghealth:heart_crystal":1,"minecraft:bucket":2,"minecraft:stone_axe":3,"minecraft:air":1222,"minecraft:gold_nugget":1,"minecraft:anvil":1,"minecraft:torch":484},"minecraft:killed_by":{"lycanitesmobs:salamander":2,"lycanitesmobs:afrit":1,"minecraft:zombie":17,"lycanitesmobs:darkling":1,"minecraft:husk":2,"minecraft:stray":7,"lycanitesmobs:roa":1,"lycanitesmobs:chupacabra":28,"mutantbeasts:mutant_enderman":1,"minecraft:zombified_piglin":6,"minecraft:creeper":1,"quark:forgotten":1,"minecraft:silverfish":1,"minecraft:cave_spider":6,"minecraft:spider":1,"mutantbeasts:mutant_skeleton":1,"lycanitesmobs:geonach":2,"minecraft:skeleton":9,"lycanitesmobs:geken":2,"lycanitesmobs:wraamon":1},"minecraft:used":{"quark:cobbled_deepslate":3,"lycanitesmobs:spawn_insect":2,"minecraft:stone":104,"minecraft:rotten_flesh":10,"minecraft:soul_sand":7,"minecraft:lily_of_the_valley":2,"lycanitesmobs:lushstonechiseled":37,"lycanitesmobs:lushstonebrick":75,"minecraft:quartz_block":1,"minecraft:music_disc_chirp":1,"minecraft:bow":926,"minecraft:furnace":7,"minecraft:cooked_cod":2,"minecraft:egg":1,"minecraft:mossy_stone_bricks":14,"minecraft:cow_spawn_egg":1,"minecraft:chorus_fruit":4,"minecraft:wooden_pickaxe":562,"minecraft:golden_apple":9,"minecraft:sand":274,"quark:marble":11,"scalinghealth:cursed_heart":7,"lycanitesmobs:cooked_arisaur_meat":12,"minecraft:birch_fence":5,"scalinghealth:enchanted_heart":5,"minecraft:diamond_sword":1401,"minecraft:wooden_sword":140,"minecraft:oak_boat":3,"minecraft:iron_bars":3,"minecraft:stone_sword":741,"minecraft:acacia_log":2,"minecraft:enchanting_table":2,"minecraft:torch":842,"minecraft:anvil":4,"minecraft:iron_axe":282,"minecraft:acacia_planks":4,"minecraft:wheat_seeds":15,"minecraft:water_bucket":138,"minecraft:rabbit":2,"lycanitesmobs:raw_chupacabra_meat":4,"minecraft:horse_spawn_egg":1,"minecraft:cracked_stone_bricks":29,"minecraft:mossy_cobblestone":47,"minecraft:orange_carpet":8,"minecraft:oak_slab":1,"minecraft:crafting_table":40,"minecraft:red_bed":2,"minecraft:white_bed":7,"lycanitesmobs:cooked_jouste_meat":2,"minecraft:oak_log":12,"minecraft:iron_pickaxe":2770,"lycanitesmobs:lushstonetile":4,"lycanitesmobs:raw_bobeko_meat":1,"minecraft:blue_carpet":9,"minecraft:cobblestone":716,"minecraft:potion":11,"minecraft:cooked_porkchop":7,"minecraft:andesite_stairs":1,"quark:oak_chest":19,"lycanitesmobs:lushstonepillar":17,"minecraft:iron_shovel":3264,"lycanitesmobs:lushcrystal":2,"minecraft:shield":427,"minecraft:iron_sword":1626,"lycanitesmobs:raw_arisaur_meat":5,"minecraft:mutton":1,"artifacts:umbrella":247,"minecraft:nether_bricks":21,"minecraft:obsidian":18,"minecraft:mossy_cobblestone_slab":8,"minecraft:stone_bricks":25,"quark:smooth_basalt":2,"minecraft:stone_pickaxe":782,"minecraft:oak_planks":32,"minecraft:ender_pearl":32,"minecraft:sugar_cane":1,"quark:cobbedstone":3,"minecraft:diamond_axe":2,"minecraft:white_wool":5,"lycanitesmobs:lushstonepolished":11,"minecraft:melon_slice":4,"minecraft:bread":56,"minecraft:string":1,"minecraft:gravel":8,"mutantbeasts:hulk_hammer":19,"lycanitesmobs:cooked_chupacabra_meat":147,"minecraft:andesite":34,"minecraft:bone_meal":21,"minecraft:cobweb":1,"minecraft:oak_fence":32,"quark:birch_chest":4,"minecraft:flint_and_steel":1,"minecraft:spruce_planks":1,"minecraft:stone_hoe":13,"lycanitesmobs:cooked_silex_meat":1,"minecraft:cooked_chicken":2,"minecraft:oak_door":4,"minecraft:dirt":2439,"scalinghealth:heart_crystal":31,"minecraft:white_carpet":10,"minecraft:spruce_fence":1,"minecraft:wooden_axe":194,"minecraft:bookshelf":22,"minecraft:oak_stairs":4,"scalinghealth:power_crystal":10,"scalinghealth:bandages":1,"minecraft:cooked_beef":17,"minecraft:enchanted_golden_apple":1,"lycanitesmobs:cooked_aspid_meat":7,"lycanitesmobs:cooked_krake_meat":1,"minecraft:cooked_mutton":8,"minecraft:iron_ore":23,"minecraft:polished_andesite":31,"minecraft:baked_potato":2,"lycanitesmobs:poisongland":3,"minecraft:cobblestone_slab":16,"minecraft:music_disc_cat":1,"minecraft:lime_bed":5,"minecraft:smoker":2,"minecraft:wooden_hoe":5,"minecraft:apple":6,"lycanitesmobs:cooked_maka_meat":15,"minecraft:chicken":1,"minecraft:stone_slab":1,"quark:root_item":39,"minecraft:stone_axe":388,"minecraft:bucket":128,"minecraft:smooth_stone":1}},"DataVersion":2586}